{
	"name": "azure_file_storage",
	"properties": {
		"type": "AzureFileStorage",
		"parameters": {
			"keyVaultSecretName": {
				"type": "String",
				"defaultValue": "andronpremfilesystem001d"
			}
		},
		"annotations": [],
		"typeProperties": {
			"connectionString": {
				"type": "AzureKeyVaultSecret",
				"store": {
					"referenceName": "azure_key_vault",
					"type": "LinkedServiceReference"
				},
				"secretName": "@{linkedService().keyVaultSecretName}"
			},
			"fileShare": "files"
		}
	}
}